edgaro/__init__.py
edgaro/balancing/__init__.py
edgaro/balancing/nested_transformer.py
edgaro/balancing/transformer.py
edgaro/balancing/transformer_array.py
edgaro/base/__init__.py
edgaro/base/base_transformer.py
edgaro/base/base_transformer_array.py
edgaro/base/utils.py
edgaro/data/__init__.py
edgaro/data/dataset.py
edgaro/data/dataset_array.py
edgaro/explain/__init__.py
edgaro/explain/explainer.py
edgaro/explain/explainer_array.py
edgaro/explain/explainer_result.py
edgaro/explain/explainer_result_array.py
edgaro/model/__init__.py
edgaro/model/model.py
edgaro/model/model_array.py
edgaro-1.0.2.2.dist-info/LICENSE
edgaro-1.0.2.2.dist-info/METADATA
edgaro-1.0.2.2.dist-info/WHEEL
edgaro-1.0.2.2.dist-info/top_level.txt
edgaro-1.0.2.2.dist-info/RECORD
