Metadata-Version: 2.2
Name: edgaro
Version: 1.0.2.2
Summary: Explainable imbalanceD learninG compARatOr
Home-page: https://github.com/adrianstando/edgaro
Author: Adrian Stańdo
Author-email: adrian.j.stando@gmail.com
Project-URL: Documentation, https://adrianstando.github.io/edgaro
Project-URL: Code repository, https://github.com/adrianstando/edgaro
Keywords: XAI,imbalance,machine learning,AI
Classifier: Development Status :: 5 - Production/Stable
Classifier: Intended Audience :: Science/Research
Classifier: Topic :: Scientific/Engineering
Classifier: Topic :: Scientific/Engineering :: Artificial Intelligence
Classifier: License :: OSI Approved :: GNU General Public License v3 (GPLv3)
Classifier: Programming Language :: Python :: 3
Classifier: Programming Language :: Python :: 3.8
Classifier: Programming Language :: Python :: 3.9
Classifier: Programming Language :: Python :: 3.10
Classifier: Programming Language :: Python :: 3 :: Only
Classifier: Operating System :: OS Independent
Requires-Python: >=3.8, <4
License-File: LICENSE
Requires-Dist: setuptools
Requires-Dist: pandas>=1.4.4
Requires-Dist: numpy>=1.20.3
Requires-Dist: dalex>=1.5.0
Requires-Dist: imbalanced-learn>=0.10.1
Requires-Dist: matplotlib>=3.4.3
Requires-Dist: openml>=0.12.2
Requires-Dist: pandas-profiling>=3.3.0
Requires-Dist: pytest>=7.1.3
Requires-Dist: scikit-learn>=1.1.0
Requires-Dist: imblearn>=0.0
Requires-Dist: xgboost>=1.5.0
Requires-Dist: scipy>=1.7.3
Requires-Dist: statsmodels>=0.13.2
Dynamic: author
Dynamic: author-email
Dynamic: classifier
Dynamic: description
Dynamic: description-content-type
Dynamic: home-page
Dynamic: keywords
Dynamic: project-url
Dynamic: requires-dist
Dynamic: requires-python
Dynamic: summary
